OncoMark/__init__.py
OncoMark/hallmark_feature.txt
OncoMark/hallmark_model.keras
OncoMark/hallmark_scaler.joblib
OncoMark/oncomark.py
OncoMark-1.0.0.dist-info/LICENSE
OncoMark-1.0.0.dist-info/METADATA
OncoMark-1.0.0.dist-info/WHEEL
OncoMark-1.0.0.dist-info/top_level.txt
OncoMark-1.0.0.dist-info/RECORD
