Metadata-Version: 2.1
Name: OncoMark
Version: 1.0.0
Summary: A deep learning tool designed to predict Cancer Hallmark activities from tumor biopsy samples.
Home-page: https://github.com/SML-CompBio/OncoMark
Author: Shreyansh Priyadarshi
Author-email: shreyansh.priyadarshi02@gmail.com
License: Apache-2.0 license
License-File: LICENSE
Requires-Dist: pandas ==2.2.3
Requires-Dist: numpy ==2.0.2
Requires-Dist: tensorflow ==2.18.0
Requires-Dist: joblib ==1.4.2
Requires-Dist: scipy ==1.14.1
